jinjagen/__init__.py
jinjagen/__main__.py
jinjagen/main.py
jinjagen-0.0.4.dist-info/METADATA
jinjagen-0.0.4.dist-info/WHEEL
jinjagen-0.0.4.dist-info/entry_points.txt
jinjagen-0.0.4.dist-info/top_level.txt
jinjagen-0.0.4.dist-info/RECORD
