Metadata-Version: 2.4
Name: jinjagen
Version: 0.0.4
Summary: A CLI tool for generating files using Jinja2 templates with smart delimiters
Author: Jet-Logic
Project-URL: Homepage, https://github.com/jet-logic/jinjagen
Project-URL: Documentation, https://github.com/jet-logic/jinjagen#readme
Project-URL: BugTracker, https://github.com/jet-logic/jinjagen/issues
Classifier: Development Status :: 4 - Beta
Classifier: Intended Audience :: Developers
Classifier: Programming Language :: Python :: 3
Classifier: Topic :: Software Development :: Code Generators
Classifier: Topic :: Utilities
Requires-Python: >=3.7
Requires-Dist: Jinja2>=3.0
Requires-Dist: PyYAML>=6.0
Provides-Extra: test
Requires-Dist: pytest; extra == "test"
Requires-Dist: pytest-cov; extra == "test"
Provides-Extra: dev
Requires-Dist: black; extra == "dev"
Requires-Dist: flake8; extra == "dev"
Requires-Dist: mypy; extra == "dev"
